MANIFEST.in
README.rst
setup.py
docs/HISTORY.txt
docs/LICENSE.GPL
docs/LICENSE.txt
ftw/__init__.py
ftw.publisher.monitor.egg-info/PKG-INFO
ftw.publisher.monitor.egg-info/SOURCES.txt
ftw.publisher.monitor.egg-info/dependency_links.txt
ftw.publisher.monitor.egg-info/entry_points.txt
ftw.publisher.monitor.egg-info/namespace_packages.txt
ftw.publisher.monitor.egg-info/not-zip-safe
ftw.publisher.monitor.egg-info/requires.txt
ftw.publisher.monitor.egg-info/top_level.txt
ftw/publisher/__init__.py
ftw/publisher/monitor/__init__.py
ftw/publisher/monitor/adapters.py
ftw/publisher/monitor/configure.zcml
ftw/publisher/monitor/handlers.py
ftw/publisher/monitor/interfaces.py
ftw/publisher/monitor/testing.py
ftw/publisher/monitor/utils.py
ftw/publisher/monitor/Extensions/__init__.py
ftw/publisher/monitor/Extensions/install.py
ftw/publisher/monitor/browser/__init__.py
ftw/publisher/monitor/browser/config.py
ftw/publisher/monitor/browser/configure.zcml
ftw/publisher/monitor/browser/mail_templates/notification_mail_html.pt
ftw/publisher/monitor/locales/ftw.publisher.monitor.pot
ftw/publisher/monitor/locales/de/LC_MESSAGES/ftw.publisher.monitor.po
ftw/publisher/monitor/profiles/default/registry.xml
ftw/publisher/monitor/profiles/uninstall/registry.xml
ftw/publisher/monitor/tests/__init__.py
ftw/publisher/monitor/tests/test_config.py
ftw/publisher/monitor/tests/test_eventhandler.py
ftw/publisher/monitor/tests/test_mailing.py
ftw/publisher/monitor/tests/test_uninstall.py
ftw/publisher/monitor/tests/test_utils.py
ftw/publisher/monitor/upgrades/__init__.py
ftw/publisher/monitor/upgrades/20200609192239_upgrade_to_registry_storage/__init__.py
ftw/publisher/monitor/upgrades/20200609192239_upgrade_to_registry_storage/registry.xml
ftw/publisher/monitor/upgrades/20200609192239_upgrade_to_registry_storage/upgrade.py
ftw/publisher/monitor/viewlets/__init__.py
ftw/publisher/monitor/viewlets/configure.zcml
ftw/publisher/monitor/viewlets/link.pt
ftw/publisher/monitor/viewlets/link.py