Metadata-Version: 2.1
Name: ftw.publisher.monitor
Version: 2.0.1
Summary: An ftw.publisher addon for monitoring the publisher queue and alerting when there is a problem.
Home-page: https://github.com/4teamwork/ftw.publisher.monitor
Author: 4teamwork AG
Author-email: mailto:info@4teamwork.ch
License: GPL2
Keywords: ftw publisher monitoring
Platform: UNKNOWN
Classifier: Framework :: Plone
Classifier: Framework :: Plone :: 4.3
Classifier: Framework :: Plone :: 5.1
Classifier: Programming Language :: Python
Classifier: Topic :: Software Development :: Libraries :: Python Modules
Provides-Extra: tests
